whisper_python/__init__.py
whisper_python/whisper_python.py
whisper_python/zeroun_intezar_agler/__init__.py
whisper_python/zeroun_intezar_agler/zeroun_intezar_agler.py
whisper_python-0.0.5.dist-info/licenses/LICENSE
whisper_python-0.0.5.dist-info/METADATA
whisper_python-0.0.5.dist-info/WHEEL
whisper_python-0.0.5.dist-info/top_level.txt
whisper_python-0.0.5.dist-info/RECORD
