Metadata-Version: 2.4
Name: whisper-python
Version: 0.0.5
Summary: whisper_python ZerounIntezarAgler
Author: Zeroun Intezar Agler
Project-URL: homepage, https://github.com/zerounintezaragler/whisper_python
Project-URL: repository, https://github.com/zerounintezaragler/whisper_python
Project-URL: documentation, https://github.com/zerounintezaragler/whisper_python
License-File: LICENSE
Dynamic: license-file
